[{"company":"Jetpulse","position":"Desktop Support Technician","jobLocation":"San Nicolas","jobStatus":"interview","jobType":"part-time","createdAt":"2024-03-27T10:40:56Z"},
{"company":"Jayo","position":"Programmer IV","jobLocation":"Malartic","jobStatus":"pending","jobType":"internship","createdAt":"2023-12-10T16:33:18Z"},
{"company":"Jatri","position":"Geologist III","jobLocation":"Sikur","jobStatus":"pending","jobType":"full-time","createdAt":"2024-04-14T05:38:23Z"},
{"company":"Dynava","position":"Assistant Professor","jobLocation":"Mizoch","jobStatus":"interview","jobType":"internship","createdAt":"2023-11-07T10:10:08Z"},
{"company":"Kare","position":"Recruiting Manager","jobLocation":"Skrunda","jobStatus":"pending","jobType":"part-time","createdAt":"2023-11-07T17:08:02Z"},
{"company":"Feednation","position":"Help Desk Operator","jobLocation":"Ko Samui","jobStatus":"declined","jobType":"full-time","createdAt":"2023-12-23T00:37:17Z"},
{"company":"Fliptune","position":"Recruiter","jobLocation":"Alcanhões","jobStatus":"interview","jobType":"internship","createdAt":"2023-09-03T02:56:34Z"},
{"company":"Meedoo","position":"Senior Developer","jobLocation":"Nogueira da Regedoura","jobStatus":"pending","jobType":"internship","createdAt":"2024-07-06T20:57:46Z"},
{"company":"DabZ","position":"Project Manager","jobLocation":"Tangzang","jobStatus":"interview","jobType":"full-time","createdAt":"2024-05-05T23:32:03Z"},
{"company":"Eabox","position":"Data Coordinator","jobLocation":"Kohlu","jobStatus":"interview","jobType":"part-time","createdAt":"2024-04-07T06:04:11Z"},
{"company":"Realcube","position":"Research Nurse","jobLocation":"Västerås","jobStatus":"interview","jobType":"full-time","createdAt":"2024-07-31T17:20:30Z"},
{"company":"Ainyx","position":"Research Assistant III","jobLocation":"Blachownia","jobStatus":"interview","jobType":"internship","createdAt":"2024-05-13T20:03:31Z"},
{"company":"Vinte","position":"Assistant Media Planner","jobLocation":"Perlez","jobStatus":"pending","jobType":"full-time","createdAt":"2024-01-28T00:07:45Z"},
{"company":"Wordpedia","position":"Structural Analysis Engineer","jobLocation":"Shuanghe","jobStatus":"declined","jobType":"internship","createdAt":"2024-08-28T15:00:00Z"},
{"company":"Thoughtblab","position":"Pharmacist","jobLocation":"Sapataria","jobStatus":"pending","jobType":"part-time","createdAt":"2023-09-16T08:58:06Z"},
{"company":"Aivee","position":"Environmental Tech","jobLocation":"Siewierz","jobStatus":"declined","jobType":"internship","createdAt":"2023-11-17T19:47:19Z"},
{"company":"Skajo","position":"Environmental Specialist","jobLocation":"Jizhou","jobStatus":"declined","jobType":"full-time","createdAt":"2024-01-09T13:44:15Z"},
{"company":"Quire","position":"Programmer III","jobLocation":"Bolekhiv","jobStatus":"interview","jobType":"full-time","createdAt":"2024-04-18T18:30:58Z"},
{"company":"Meejo","position":"Research Associate","jobLocation":"Sawankhalok","jobStatus":"declined","jobType":"part-time","createdAt":"2023-11-21T20:59:07Z"},
{"company":"Flashpoint","position":"Recruiting Manager","jobLocation":"Cilegi","jobStatus":"declined","jobType":"internship","createdAt":"2024-07-08T08:20:07Z"},
{"company":"Skiptube","position":"Software Consultant","jobLocation":"Montbéliard","jobStatus":"interview","jobType":"part-time","createdAt":"2024-06-12T09:47:59Z"},
{"company":"Mycat","position":"Programmer II","jobLocation":"Mayong","jobStatus":"declined","jobType":"internship","createdAt":"2024-04-29T20:47:04Z"},
{"company":"Wikibox","position":"Recruiting Manager","jobLocation":"Duncan Town","jobStatus":"pending","jobType":"internship","createdAt":"2023-12-17T07:35:18Z"},
{"company":"Linkbridge","position":"Computer Systems Analyst I","jobLocation":"Birinci Aşıqlı","jobStatus":"declined","jobType":"internship","createdAt":"2024-07-19T08:00:19Z"},
{"company":"Zooveo","position":"Director of Sales","jobLocation":"Turpay","jobStatus":"declined","jobType":"part-time","createdAt":"2024-08-23T06:53:54Z"},
{"company":"Kazio","position":"Mechanical Systems Engineer","jobLocation":"Pamotan","jobStatus":"interview","jobType":"internship","createdAt":"2023-09-19T12:35:38Z"},
{"company":"Dabfeed","position":"Human Resources Assistant IV","jobLocation":"Ban Tak","jobStatus":"declined","jobType":"full-time","createdAt":"2023-11-04T20:28:24Z"},
{"company":"Vinder","position":"Sales Associate","jobLocation":"Uummannaq","jobStatus":"declined","jobType":"internship","createdAt":"2023-08-31T20:30:36Z"},
{"company":"Geba","position":"Web Developer III","jobLocation":"Kuruman","jobStatus":"declined","jobType":"full-time","createdAt":"2024-05-01T19:38:30Z"},
{"company":"Jatri","position":"Software Test Engineer IV","jobLocation":"Esparza","jobStatus":"interview","jobType":"internship","createdAt":"2023-10-01T05:46:56Z"},
{"company":"Twitternation","position":"Research Assistant III","jobLocation":"San Luis","jobStatus":"interview","jobType":"full-time","createdAt":"2023-08-31T14:10:47Z"},
{"company":"BlogXS","position":"VP Marketing","jobLocation":"Limoges","jobStatus":"interview","jobType":"part-time","createdAt":"2024-01-06T17:42:34Z"},
{"company":"Flashspan","position":"Web Designer IV","jobLocation":"La Hacienda","jobStatus":"interview","jobType":"internship","createdAt":"2024-03-05T21:05:36Z"},
{"company":"Youtags","position":"Web Designer II","jobLocation":"Kobylin","jobStatus":"declined","jobType":"part-time","createdAt":"2024-05-01T19:03:09Z"},
{"company":"Meejo","position":"Analog Circuit Design manager","jobLocation":"Caraga","jobStatus":"pending","jobType":"full-time","createdAt":"2024-02-02T14:33:28Z"},
{"company":"Realfire","position":"Sales Representative","jobLocation":"Tagana-an","jobStatus":"declined","jobType":"part-time","createdAt":"2023-10-08T11:13:54Z"},
{"company":"Eayo","position":"Environmental Tech","jobLocation":"Tiantang","jobStatus":"declined","jobType":"internship","createdAt":"2023-11-27T03:04:24Z"},
{"company":"Bluezoom","position":"Web Developer IV","jobLocation":"Jabon","jobStatus":"declined","jobType":"full-time","createdAt":"2024-08-26T20:50:48Z"},
{"company":"Eabox","position":"Engineer III","jobLocation":"Caleta Cruz","jobStatus":"interview","jobType":"part-time","createdAt":"2024-07-09T14:24:21Z"},
{"company":"Oyoloo","position":"Software Engineer IV","jobLocation":"Voskehask","jobStatus":"pending","jobType":"full-time","createdAt":"2024-06-01T22:39:11Z"},
{"company":"Oyoloo","position":"VP Accounting","jobLocation":"Medellin","jobStatus":"interview","jobType":"part-time","createdAt":"2024-01-14T07:03:16Z"},
{"company":"Kayveo","position":"Budget/Accounting Analyst III","jobLocation":"Berlin","jobStatus":"interview","jobType":"internship","createdAt":"2024-06-12T05:28:59Z"},
{"company":"Mynte","position":"Senior Cost Accountant","jobLocation":"Artsvanist","jobStatus":"declined","jobType":"full-time","createdAt":"2023-10-23T10:06:09Z"},
{"company":"Skilith","position":"Business Systems Development Analyst","jobLocation":"Tai Po","jobStatus":"interview","jobType":"internship","createdAt":"2023-11-24T07:12:19Z"},
{"company":"Skyba","position":"Speech Pathologist","jobLocation":"Valença do Piauí","jobStatus":"interview","jobType":"full-time","createdAt":"2024-05-30T15:14:33Z"},
{"company":"Bubblebox","position":"Senior Financial Analyst","jobLocation":"Huangsha","jobStatus":"declined","jobType":"full-time","createdAt":"2024-04-18T10:14:02Z"},
{"company":"Skimia","position":"Speech Pathologist","jobLocation":"Ngepoh Kidul","jobStatus":"interview","jobType":"part-time","createdAt":"2024-07-27T22:07:56Z"},
{"company":"Jabbersphere","position":"Librarian","jobLocation":"Kuantan","jobStatus":"interview","jobType":"part-time","createdAt":"2023-10-31T19:13:52Z"},
{"company":"Riffwire","position":"Junior Executive","jobLocation":"Staroutkinsk","jobStatus":"interview","jobType":"internship","createdAt":"2024-08-27T20:56:29Z"},
{"company":"Yambee","position":"Office Assistant II","jobLocation":"Kayes","jobStatus":"pending","jobType":"internship","createdAt":"2024-02-22T20:46:39Z"},
{"company":"Chatterbridge","position":"Account Representative I","jobLocation":"Aristóbulo del Valle","jobStatus":"interview","jobType":"internship","createdAt":"2023-09-12T10:32:18Z"},
{"company":"Dynabox","position":"Research Nurse","jobLocation":"Cuijiaqiao","jobStatus":"declined","jobType":"part-time","createdAt":"2024-05-07T22:33:37Z"},
{"company":"Tazzy","position":"Analyst Programmer","jobLocation":"Baojia","jobStatus":"interview","jobType":"internship","createdAt":"2024-08-21T18:22:37Z"},
{"company":"Oyonder","position":"Senior Developer","jobLocation":"Coja","jobStatus":"interview","jobType":"full-time","createdAt":"2024-08-19T10:42:29Z"},
{"company":"Mydeo","position":"Executive Secretary","jobLocation":"Kangping","jobStatus":"interview","jobType":"internship","createdAt":"2024-03-10T03:14:05Z"},
{"company":"Yacero","position":"Software Test Engineer II","jobLocation":"Saray","jobStatus":"pending","jobType":"internship","createdAt":"2024-07-02T18:41:12Z"},
{"company":"Minyx","position":"Senior Developer","jobLocation":"Chyżne","jobStatus":"declined","jobType":"part-time","createdAt":"2024-07-19T04:55:28Z"},
{"company":"Yakidoo","position":"Assistant Professor","jobLocation":"Fiães","jobStatus":"interview","jobType":"internship","createdAt":"2024-04-15T02:10:14Z"},
{"company":"Gabtune","position":"Senior Cost Accountant","jobLocation":"Odintsovo","jobStatus":"interview","jobType":"part-time","createdAt":"2024-08-12T02:08:10Z"},
{"company":"Dablist","position":"Registered Nurse","jobLocation":"Fulong","jobStatus":"pending","jobType":"part-time","createdAt":"2023-09-23T09:08:10Z"},
{"company":"Youbridge","position":"Business Systems Development Analyst","jobLocation":"São Pedro","jobStatus":"pending","jobType":"full-time","createdAt":"2024-03-03T10:21:58Z"},
{"company":"Blognation","position":"Accountant II","jobLocation":"Melong","jobStatus":"declined","jobType":"full-time","createdAt":"2024-08-19T23:22:55Z"},
{"company":"Dabjam","position":"Project Manager","jobLocation":"Rautjärvi","jobStatus":"declined","jobType":"full-time","createdAt":"2024-04-08T00:15:33Z"},
{"company":"Gabtype","position":"Senior Quality Engineer","jobLocation":"Changle","jobStatus":"pending","jobType":"full-time","createdAt":"2024-08-01T02:30:00Z"},
{"company":"Thoughtmix","position":"Information Systems Manager","jobLocation":"Orlovskiy","jobStatus":"interview","jobType":"internship","createdAt":"2024-07-28T02:31:15Z"},
{"company":"Feedfish","position":"Structural Analysis Engineer","jobLocation":"Épinal","jobStatus":"pending","jobType":"internship","createdAt":"2023-11-19T19:18:09Z"},
{"company":"Dynabox","position":"Structural Analysis Engineer","jobLocation":"Telouet","jobStatus":"interview","jobType":"full-time","createdAt":"2023-10-02T11:19:20Z"},
{"company":"Zazio","position":"Health Coach III","jobLocation":"Bouabout","jobStatus":"declined","jobType":"full-time","createdAt":"2023-10-27T11:52:37Z"},
{"company":"Midel","position":"VP Product Management","jobLocation":"Miami","jobStatus":"interview","jobType":"internship","createdAt":"2024-01-07T18:51:34Z"},
{"company":"Flashspan","position":"Senior Cost Accountant","jobLocation":"Linshe","jobStatus":"interview","jobType":"full-time","createdAt":"2024-02-16T02:10:32Z"},
{"company":"Npath","position":"Web Developer I","jobLocation":"Guifeng","jobStatus":"declined","jobType":"full-time","createdAt":"2023-12-25T06:17:24Z"},
{"company":"Riffpath","position":"Nurse","jobLocation":"Pyhäntä","jobStatus":"declined","jobType":"full-time","createdAt":"2023-11-17T17:20:26Z"},
{"company":"Topicshots","position":"Human Resources Manager","jobLocation":"Ganjiang","jobStatus":"interview","jobType":"internship","createdAt":"2024-07-13T10:25:59Z"},
{"company":"Plambee","position":"Media Manager I","jobLocation":"Casa Nova","jobStatus":"pending","jobType":"internship","createdAt":"2024-03-07T18:26:38Z"},
{"company":"Tagcat","position":"Executive Secretary","jobLocation":"Khombole","jobStatus":"interview","jobType":"internship","createdAt":"2024-02-27T15:58:06Z"},
{"company":"Snaptags","position":"Geological Engineer","jobLocation":"Frei","jobStatus":"declined","jobType":"full-time","createdAt":"2023-10-18T09:39:28Z"},
{"company":"Flipbug","position":"Account Representative I","jobLocation":"Al Jadīd","jobStatus":"interview","jobType":"part-time","createdAt":"2024-03-30T09:18:01Z"},
{"company":"Voonte","position":"Statistician III","jobLocation":"Dongpu","jobStatus":"declined","jobType":"full-time","createdAt":"2024-01-20T04:49:49Z"},
{"company":"Livefish","position":"Nuclear Power Engineer","jobLocation":"Hadžići","jobStatus":"pending","jobType":"part-time","createdAt":"2024-04-12T03:32:55Z"},
{"company":"Meevee","position":"Automation Specialist IV","jobLocation":"Kortkeros","jobStatus":"interview","jobType":"full-time","createdAt":"2024-06-23T23:49:54Z"},
{"company":"Innojam","position":"Social Worker","jobLocation":"Kyzylzhar","jobStatus":"pending","jobType":"part-time","createdAt":"2023-09-27T20:50:56Z"},
{"company":"Zoombox","position":"Internal Auditor","jobLocation":"Toluviejo","jobStatus":"declined","jobType":"internship","createdAt":"2024-01-18T16:58:12Z"},
{"company":"Yadel","position":"Computer Systems Analyst IV","jobLocation":"Shijiazhuang","jobStatus":"pending","jobType":"part-time","createdAt":"2023-09-27T15:38:41Z"},
{"company":"Photobean","position":"Senior Developer","jobLocation":"Kolbano","jobStatus":"interview","jobType":"internship","createdAt":"2023-09-26T19:16:10Z"},
{"company":"Thoughtmix","position":"Associate Professor","jobLocation":"Phoenix","jobStatus":"pending","jobType":"full-time","createdAt":"2023-09-06T19:37:45Z"},
{"company":"Yambee","position":"VP Marketing","jobLocation":"Boronów","jobStatus":"interview","jobType":"part-time","createdAt":"2024-04-06T13:10:59Z"},
{"company":"Pixoboo","position":"Structural Analysis Engineer","jobLocation":"Kapshagay","jobStatus":"declined","jobType":"full-time","createdAt":"2023-10-16T19:28:23Z"},
{"company":"Yambee","position":"Chief Design Engineer","jobLocation":"Staropavlovskaya","jobStatus":"declined","jobType":"full-time","createdAt":"2024-02-24T10:19:17Z"},
{"company":"Quinu","position":"Recruiter","jobLocation":"Khotsimsk","jobStatus":"pending","jobType":"part-time","createdAt":"2023-11-15T09:35:22Z"},
{"company":"InnoZ","position":"Programmer I","jobLocation":"Boulder","jobStatus":"declined","jobType":"part-time","createdAt":"2024-05-25T22:14:18Z"},
{"company":"Feedbug","position":"Junior Executive","jobLocation":"Blois","jobStatus":"interview","jobType":"full-time","createdAt":"2023-10-21T07:53:50Z"},
{"company":"Linklinks","position":"Compensation Analyst","jobLocation":"Donostia-San Sebastian","jobStatus":"interview","jobType":"internship","createdAt":"2024-06-15T22:27:14Z"},
{"company":"Mynte","position":"Accountant III","jobLocation":"Tadabliro","jobStatus":"interview","jobType":"internship","createdAt":"2023-11-06T17:23:05Z"},
{"company":"Tambee","position":"Nuclear Power Engineer","jobLocation":"Vilar do Monte","jobStatus":"declined","jobType":"full-time","createdAt":"2023-11-26T11:22:55Z"},
{"company":"Shuffletag","position":"Graphic Designer","jobLocation":"Uba","jobStatus":"pending","jobType":"part-time","createdAt":"2024-06-22T18:54:24Z"},
{"company":"Fiveclub","position":"Programmer II","jobLocation":"Lajedo","jobStatus":"interview","jobType":"full-time","createdAt":"2023-10-16T16:14:25Z"},
{"company":"Buzzshare","position":"Geologist III","jobLocation":"Pasireurih","jobStatus":"interview","jobType":"full-time","createdAt":"2023-10-12T16:06:24Z"},
{"company":"Youtags","position":"Administrative Officer","jobLocation":"Pekuwon","jobStatus":"declined","jobType":"full-time","createdAt":"2023-10-29T12:13:42Z"},
{"company":"Eayo","position":"Marketing Assistant","jobLocation":"Zhuhong","jobStatus":"declined","jobType":"full-time","createdAt":"2024-04-10T14:13:30Z"},
{"company":"Lazzy","position":"Speech Pathologist","jobLocation":"Līgatne","jobStatus":"interview","jobType":"full-time","createdAt":"2023-11-13T02:03:53Z"}]